xlsxviewer/__init__.py
xlsxviewer/utils.py
xlsxviewer-0.1.3.dist-info/LICENSE
xlsxviewer-0.1.3.dist-info/METADATA
xlsxviewer-0.1.3.dist-info/WHEEL
xlsxviewer-0.1.3.dist-info/entry_points.txt
xlsxviewer-0.1.3.dist-info/top_level.txt
xlsxviewer-0.1.3.dist-info/RECORD
